MANIFEST.in
README.rst
setup.py
flask_nemo/__init__.py
flask_nemo/_data.py
flask_nemo/chunker.py
flask_nemo/cmd.py
flask_nemo/common.py
flask_nemo/errors.py
flask_nemo/filters.py
flask_nemo/jinjaext.py
flask_nemo/plugin.py
flask_nemo.egg-info/PKG-INFO
flask_nemo.egg-info/SOURCES.txt
flask_nemo.egg-info/dependency_links.txt
flask_nemo.egg-info/entry_points.txt
flask_nemo.egg-info/not-zip-safe
flask_nemo.egg-info/requires.txt
flask_nemo.egg-info/top_level.txt
flask_nemo/data/epidoc.xsl
flask_nemo/data/i18n/languages.json
flask_nemo/data/static/css/bootstrap.min.css
flask_nemo/data/static/css/theme.min.css
flask_nemo/data/static/images/logo.png
flask_nemo/data/static/images/nemo.png
flask_nemo/data/templates/breadcrumb.html
flask_nemo/data/templates/collection.html
flask_nemo/data/templates/container.html
flask_nemo/data/templates/footer.html
flask_nemo/data/templates/index.html
flask_nemo/data/templates/logo.html
flask_nemo/data/templates/macros.html
flask_nemo/data/templates/menu.html
flask_nemo/data/templates/metadata.html
flask_nemo/data/templates/passage_footer.html
flask_nemo/data/templates/references.html
flask_nemo/data/templates/text.html
flask_nemo/data/templates_plugins/breadcrumb/breadcrumb.html
flask_nemo/plugins/__init__.py
flask_nemo/plugins/annotations_api.py
flask_nemo/plugins/default.py
flask_nemo/query/__init__.py
flask_nemo/query/annotation.py
flask_nemo/query/interface.py
flask_nemo/query/proto.py
flask_nemo/query/resolve.py
tests/test_default/__init__.py
tests/test_default/test_breadcrumb.py
tests/test_plugin/__init__.py
tests/test_plugin/test_assets.py
tests/test_plugin/test_filters.py
tests/test_plugin/test_resources.py
tests/test_plugin/test_routes.py
tests/test_plugins/__init__.py
tests/test_plugins/test_annotations_api.py
tests/test_plugins/test_resources.py
tests/test_query/__init__.py
tests/test_query/test_annotation.py
tests/test_query/test_interface.py
tests/test_query/test_query.py
tests/test_query/test_retriever.py