Metadata-Version: 1.0
Name: flask-nemo
Version: 1.0.2
Summary: Flask Extension to browse CTS Repository
Home-page: https://github.com/capitains/flask-capitains-nemo
Author: Thibault Clerice
Author-email: leponteineptique@gmail.com
License: Mozilla Public License Version 2.0
Platform: UNKNOWN
